<annotations><filename>1551.jpg</filename><folder>images/1551.jpg</folder><size><width>500</width><height>356</height><depth>3</depth></size><object><name>short_gun</name><pose>Unspecified</pose><truncated>0</truncated><difficult>0</difficult><bndbox><xmin>267</xmin><ymin>2</ymin><xmax>437</xmax><ymax>98</ymax></bndbox></object><object><name>short_gun</name><pose>Unspecified</pose><truncated>0</truncated><difficult>0</difficult><bndbox><xmin>318</xmin><ymin>97</ymin><xmax>452</xmax><ymax>191</ymax></bndbox></object><object><name>short_gun</name><pose>Unspecified</pose><truncated>0</truncated><difficult>0</difficult><bndbox><xmin>316</xmin><ymin>199</ymin><xmax>467</xmax><ymax>314</ymax></bndbox></object><object><name>short_gun</name><pose>Unspecified</pose><truncated>0</truncated><difficult>0</difficult><bndbox><xmin>235</xmin><ymin>231</ymin><xmax>351</xmax><ymax>326</ymax></bndbox></object><object><name>short_gun</name><pose>Unspecified</pose><truncated>0</truncated><difficult>0</difficult><bndbox><xmin>185</xmin><ymin>128</ymin><xmax>351</xmax><ymax>245</ymax></bndbox></object><object><name>short_gun</name><pose>Unspecified</pose><truncated>0</truncated><difficult>0</difficult><bndbox><xmin>178</xmin><ymin>29</ymin><xmax>303</xmax><ymax>132</ymax></bndbox></object><object><name>short_gun</name><pose>Unspecified</pose><truncated>0</truncated><difficult>0</difficult><bndbox><xmin>102</xmin><ymin>84</ymin><xmax>214</xmax><ymax>135</ymax></bndbox></object><object><name>short_gun</name><pose>Unspecified</pose><truncated>0</truncated><difficult>0</difficult><bndbox><xmin>30</xmin><ymin>2</ymin><xmax>214</xmax><ymax>141</ymax></bndbox></object><object><name>short_gun</name><pose>Unspecified</pose><truncated>0</truncated><difficult>0</difficult><bndbox><xmin>1</xmin><ymin>147</ymin><xmax>181</xmax><ymax>253</ymax></bndbox></object><object><name>short_gun</name><pose>Unspecified</pose><truncated>0</truncated><difficult>0</difficult><bndbox><xmin>23</xmin><ymin>223</ymin><xmax>179</xmax><ymax>326</ymax></bndbox></object></annotations>